[
{
  "datetime": "2025-1206-1834",
  "pressure": 1022
}
,
{
  "datetime": "2025-1206-1841",
  "pressure": 1022
}
,
{
  "datetime": "2025-1206-1850",
  "pressure": 1022
}
,
{
  "datetime": "2025-1206-1900",
  "pressure": 1022
}
,
{
  "datetime": "2025-1206-1914",
  "pressure": 1022
}
,
{
  "datetime": "2025-1206-1926",
  "pressure": 1022
}
,
{
  "datetime": "2025-1206-1936",
  "pressure": 1021
}
,
{
  "datetime": "2025-1206-1943",
  "pressure": 1021
}
,
{
  "datetime": "2025-1206-1950",
  "pressure": 1021
}
,
{
  "datetime": "2025-1206-2000",
  "pressure": 1021
}
,
{
  "datetime": "2025-1206-2013",
  "pressure": 1021
}
,
{
  "datetime": "2025-1206-2023",
  "pressure": 1021
}
,
{
  "datetime": "2025-1206-2030",
  "pressure": 1021
}
,
{
  "datetime": "2025-1206-2041",
  "pressure": 1021
}
,
{
  "datetime": "2025-1206-2050",
  "pressure": 1021
}
,
{
  "datetime": "2025-1206-2100",
  "pressure": 1021
}
,
{
  "datetime": "2025-1206-2115",
  "pressure": 1021
}
,
{
  "datetime": "2025-1206-2130",
  "pressure": 1021
}
,
{
  "datetime": "2025-1206-2154",
  "pressure": 1021
}
,
{
  "datetime": "2025-1206-2207",
  "pressure": 1021
}
,
{
  "datetime": "2025-1206-2218",
  "pressure": 1021
}
,
{
  "datetime": "2025-1206-2232",
  "pressure": 1021
}
,
{
  "datetime": "2025-1206-2242",
  "pressure": 1021
}
,
{
  "datetime": "2025-1206-2250",
  "pressure": 1021
}
,
{
  "datetime": "2025-1206-2300",
  "pressure": 1021
}
,
{
  "datetime": "2025-1206-2313",
  "pressure": 1021
}
,
{
  "datetime": "2025-1206-2325",
  "pressure": 1021
}
,
{
  "datetime": "2025-1206-2333",
  "pressure": 1020
}
,
{
  "datetime": "2025-1206-2342",
  "pressure": 1020
}
,
{
  "datetime": "2025-1206-2350",
  "pressure": 1020
}
,
{
  "datetime": "2025-1207-0000",
  "pressure": 1020
}
,
{
  "datetime": "2025-1207-0014",
  "pressure": 1020
}
,
{
  "datetime": "2025-1207-0025",
  "pressure": 1020
}
,
{
  "datetime": "2025-1207-0032",
  "pressure": 1020
}
,
{
  "datetime": "2025-1207-0041",
  "pressure": 1020
}
,
{
  "datetime": "2025-1207-0050",
  "pressure": 1020
}
,
{
  "datetime": "2025-1207-0100",
  "pressure": 1020
}
,
{
  "datetime": "2025-1207-0114",
  "pressure": 1020
}
,
{
  "datetime": "2025-1207-0127",
  "pressure": 1020
}
,
{
  "datetime": "2025-1207-0138",
  "pressure": 1019
}
,
{
  "datetime": "2025-1207-0147",
  "pressure": 1019
}
,
{
  "datetime": "2025-1207-0153",
  "pressure": 1019
}
,
{
  "datetime": "2025-1207-0200",
  "pressure": 1019
}
,
{
  "datetime": "2025-1207-0213",
  "pressure": 1019
}
,
{
  "datetime": "2025-1207-0225",
  "pressure": 1019
}
,
{
  "datetime": "2025-1207-0232",
  "pressure": 1019
}
,
{
  "datetime": "2025-1207-0241",
  "pressure": 1019
}
,
{
  "datetime": "2025-1207-0250",
  "pressure": 1019
}
,
{
  "datetime": "2025-1207-0300",
  "pressure": 1019
}
,
{
  "datetime": "2025-1207-0315",
  "pressure": 1019
}
,
{
  "datetime": "2025-1207-0328",
  "pressure": 1019
}
,
{
  "datetime": "2025-1207-0340",
  "pressure": 1018
}
,
{
  "datetime": "2025-1207-0351",
  "pressure": 1019
}
,
{
  "datetime": "2025-1207-0400",
  "pressure": 1019
}
,
{
  "datetime": "2025-1207-0413",
  "pressure": 1019
}
,
{
  "datetime": "2025-1207-0423",
  "pressure": 1019
}
,
{
  "datetime": "2025-1207-0430",
  "pressure": 1019
}
,
{
  "datetime": "2025-1207-0440",
  "pressure": 1018
}
,
{
  "datetime": "2025-1207-0450",
  "pressure": 1018
}
,
{
  "datetime": "2025-1207-0500",
  "pressure": 1018
}
,
{
  "datetime": "2025-1207-0514",
  "pressure": 1018
}
,
{
  "datetime": "2025-1207-0527",
  "pressure": 1018
}
,
{
  "datetime": "2025-1207-0535",
  "pressure": 1018
}
,
{
  "datetime": "2025-1207-0542",
  "pressure": 1019
}
,
{
  "datetime": "2025-1207-0550",
  "pressure": 1019
}
,
{
  "datetime": "2025-1207-0600",
  "pressure": 1019
}
,
{
  "datetime": "2025-1207-0614",
  "pressure": 1019
}
,
{
  "datetime": "2025-1207-0624",
  "pressure": 1019
}
,
{
  "datetime": "2025-1207-0631",
  "pressure": 1019
}
,
{
  "datetime": "2025-1207-0641",
  "pressure": 1019
}
,
{
  "datetime": "2025-1207-0650",
  "pressure": 1019
}
,
{
  "datetime": "2025-1207-0700",
  "pressure": 1019
}
,
{
  "datetime": "2025-1207-0714",
  "pressure": 1019
}
,
{
  "datetime": "2025-1207-0726",
  "pressure": 1019
}
,
{
  "datetime": "2025-1207-0735",
  "pressure": 1019
}
,
{
  "datetime": "2025-1207-0742",
  "pressure": 1019
}
,
{
  "datetime": "2025-1207-0750",
  "pressure": 1019
}
,
{
  "datetime": "2025-1207-0800",
  "pressure": 1019
}
,
{
  "datetime": "2025-1207-0814",
  "pressure": 1019
}
,
{
  "datetime": "2025-1207-0825",
  "pressure": 1019
}
,
{
  "datetime": "2025-1207-0832",
  "pressure": 1020
}
,
{
  "datetime": "2025-1207-0841",
  "pressure": 1020
}
,
{
  "datetime": "2025-1207-0850",
  "pressure": 1020
}
,
{
  "datetime": "2025-1207-0901",
  "pressure": 1020
}
,
{
  "datetime": "2025-1207-0942",
  "pressure": 1020
}
,
{
  "datetime": "2025-1207-1014",
  "pressure": 1020
}
,
{
  "datetime": "2025-1207-1057",
  "pressure": 1019
}
,
{
  "datetime": "2025-1207-1143",
  "pressure": 1018
}
,
{
  "datetime": "2025-1207-1217",
  "pressure": 1018
}
,
{
  "datetime": "2025-1207-1246",
  "pressure": 1018
}
,
{
  "datetime": "2025-1207-1305",
  "pressure": 1018
}
,
{
  "datetime": "2025-1207-1320",
  "pressure": 1018
}
,
{
  "datetime": "2025-1207-1339",
  "pressure": 1018
}
,
{
  "datetime": "2025-1207-1350",
  "pressure": 1018
}
,
{
  "datetime": "2025-1207-1356",
  "pressure": 1018
}
,
{
  "datetime": "2025-1207-1403",
  "pressure": 1018
}
,
{
  "datetime": "2025-1207-1414",
  "pressure": 1018
}
,
{
  "datetime": "2025-1207-1426",
  "pressure": 1018
}
,
{
  "datetime": "2025-1207-1435",
  "pressure": 1018
}
,
{
  "datetime": "2025-1207-1442",
  "pressure": 1018
}
,
{
  "datetime": "2025-1207-1451",
  "pressure": 1018
}
,
{
  "datetime": "2025-1207-1500",
  "pressure": 1018
}
,
{
  "datetime": "2025-1207-1515",
  "pressure": 1018
}
,
{
  "datetime": "2025-1207-1528",
  "pressure": 1018
}
,
{
  "datetime": "2025-1207-1542",
  "pressure": 1018
}
,
{
  "datetime": "2025-1207-1552",
  "pressure": 1018
}
,
{
  "datetime": "2025-1207-1600",
  "pressure": 1018
}
,
{
  "datetime": "2025-1207-1614",
  "pressure": 1018
}
,
{
  "datetime": "2025-1207-1625",
  "pressure": 1018
}
,
{
  "datetime": "2025-1207-1631",
  "pressure": 1018
}
,
{
  "datetime": "2025-1207-1640",
  "pressure": 1018
}
,
{
  "datetime": "2025-1207-1650",
  "pressure": 1018
}
,
{
  "datetime": "2025-1207-1700",
  "pressure": 1018
}
,
{
  "datetime": "2025-1207-1714",
  "pressure": 1018
}
,
{
  "datetime": "2025-1207-1727",
  "pressure": 1018
}
,
{
  "datetime": "2025-1207-1738",
  "pressure": 1018
}
,
{
  "datetime": "2025-1207-1746",
  "pressure": 1018
}
,
{
  "datetime": "2025-1207-1752",
  "pressure": 1018
}
,
{
  "datetime": "2025-1207-1800",
  "pressure": 1018
}
,
{
  "datetime": "2025-1207-1814",
  "pressure": 1018
}
,
{
  "datetime": "2025-1207-1826",
  "pressure": 1018
}
,
{
  "datetime": "2025-1207-1833",
  "pressure": 1019
}
]
