[
{
  "datetime": "2025-1205-2243",
  "pressure": 1021
}
,
{
  "datetime": "2025-1205-2252",
  "pressure": 1021
}
,
{
  "datetime": "2025-1205-2300",
  "pressure": 1021
}
,
{
  "datetime": "2025-1205-2314",
  "pressure": 1021
}
,
{
  "datetime": "2025-1205-2327",
  "pressure": 1021
}
,
{
  "datetime": "2025-1205-2338",
  "pressure": 1021
}
,
{
  "datetime": "2025-1205-2346",
  "pressure": 1021
}
,
{
  "datetime": "2025-1205-2352",
  "pressure": 1021
}
,
{
  "datetime": "2025-1206-0001",
  "pressure": 1021
}
,
{
  "datetime": "2025-1206-0014",
  "pressure": 1021
}
,
{
  "datetime": "2025-1206-0027",
  "pressure": 1021
}
,
{
  "datetime": "2025-1206-0038",
  "pressure": 1022
}
,
{
  "datetime": "2025-1206-0046",
  "pressure": 1022
}
,
{
  "datetime": "2025-1206-0052",
  "pressure": 1022
}
,
{
  "datetime": "2025-1206-0100",
  "pressure": 1022
}
,
{
  "datetime": "2025-1206-0115",
  "pressure": 1022
}
,
{
  "datetime": "2025-1206-0128",
  "pressure": 1022
}
,
{
  "datetime": "2025-1206-0141",
  "pressure": 1022
}
,
{
  "datetime": "2025-1206-0154",
  "pressure": 1022
}
,
{
  "datetime": "2025-1206-0201",
  "pressure": 1022
}
,
{
  "datetime": "2025-1206-0214",
  "pressure": 1022
}
,
{
  "datetime": "2025-1206-0226",
  "pressure": 1022
}
,
{
  "datetime": "2025-1206-0235",
  "pressure": 1023
}
,
{
  "datetime": "2025-1206-0242",
  "pressure": 1023
}
,
{
  "datetime": "2025-1206-0250",
  "pressure": 1023
}
,
{
  "datetime": "2025-1206-0300",
  "pressure": 1023
}
,
{
  "datetime": "2025-1206-0318",
  "pressure": 1023
}
,
{
  "datetime": "2025-1206-0332",
  "pressure": 1022
}
,
{
  "datetime": "2025-1206-0345",
  "pressure": 1022
}
,
{
  "datetime": "2025-1206-0354",
  "pressure": 1022
}
,
{
  "datetime": "2025-1206-0400",
  "pressure": 1022
}
,
{
  "datetime": "2025-1206-0413",
  "pressure": 1022
}
,
{
  "datetime": "2025-1206-0425",
  "pressure": 1022
}
,
{
  "datetime": "2025-1206-0431",
  "pressure": 1023
}
,
{
  "datetime": "2025-1206-0441",
  "pressure": 1023
}
,
{
  "datetime": "2025-1206-0450",
  "pressure": 1023
}
,
{
  "datetime": "2025-1206-0500",
  "pressure": 1023
}
,
{
  "datetime": "2025-1206-0514",
  "pressure": 1023
}
,
{
  "datetime": "2025-1206-0527",
  "pressure": 1023
}
,
{
  "datetime": "2025-1206-0537",
  "pressure": 1023
}
,
{
  "datetime": "2025-1206-0545",
  "pressure": 1023
}
,
{
  "datetime": "2025-1206-0552",
  "pressure": 1023
}
,
{
  "datetime": "2025-1206-0600",
  "pressure": 1023
}
,
{
  "datetime": "2025-1206-0614",
  "pressure": 1023
}
,
{
  "datetime": "2025-1206-0626",
  "pressure": 1023
}
,
{
  "datetime": "2025-1206-0633",
  "pressure": 1024
}
,
{
  "datetime": "2025-1206-0642",
  "pressure": 1024
}
,
{
  "datetime": "2025-1206-0650",
  "pressure": 1024
}
,
{
  "datetime": "2025-1206-0700",
  "pressure": 1024
}
,
{
  "datetime": "2025-1206-0714",
  "pressure": 1024
}
,
{
  "datetime": "2025-1206-0726",
  "pressure": 1024
}
,
{
  "datetime": "2025-1206-0736",
  "pressure": 1025
}
,
{
  "datetime": "2025-1206-0743",
  "pressure": 1025
}
,
{
  "datetime": "2025-1206-0750",
  "pressure": 1025
}
,
{
  "datetime": "2025-1206-0800",
  "pressure": 1025
}
,
{
  "datetime": "2025-1206-0814",
  "pressure": 1025
}
,
{
  "datetime": "2025-1206-0826",
  "pressure": 1025
}
,
{
  "datetime": "2025-1206-0833",
  "pressure": 1025
}
,
{
  "datetime": "2025-1206-0841",
  "pressure": 1025
}
,
{
  "datetime": "2025-1206-0850",
  "pressure": 1025
}
,
{
  "datetime": "2025-1206-0901",
  "pressure": 1025
}
,
{
  "datetime": "2025-1206-0936",
  "pressure": 1025
}
,
{
  "datetime": "2025-1206-1002",
  "pressure": 1025
}
,
{
  "datetime": "2025-1206-1042",
  "pressure": 1024
}
,
{
  "datetime": "2025-1206-1120",
  "pressure": 1024
}
,
{
  "datetime": "2025-1206-1156",
  "pressure": 1023
}
,
{
  "datetime": "2025-1206-1220",
  "pressure": 1023
}
,
{
  "datetime": "2025-1206-1242",
  "pressure": 1022
}
,
{
  "datetime": "2025-1206-1255",
  "pressure": 1022
}
,
{
  "datetime": "2025-1206-1301",
  "pressure": 1022
}
,
{
  "datetime": "2025-1206-1314",
  "pressure": 1022
}
,
{
  "datetime": "2025-1206-1327",
  "pressure": 1022
}
,
{
  "datetime": "2025-1206-1337",
  "pressure": 1022
}
,
{
  "datetime": "2025-1206-1345",
  "pressure": 1022
}
,
{
  "datetime": "2025-1206-1351",
  "pressure": 1022
}
,
{
  "datetime": "2025-1206-1400",
  "pressure": 1022
}
,
{
  "datetime": "2025-1206-1414",
  "pressure": 1022
}
,
{
  "datetime": "2025-1206-1426",
  "pressure": 1022
}
,
{
  "datetime": "2025-1206-1436",
  "pressure": 1022
}
,
{
  "datetime": "2025-1206-1443",
  "pressure": 1022
}
,
{
  "datetime": "2025-1206-1450",
  "pressure": 1022
}
,
{
  "datetime": "2025-1206-1500",
  "pressure": 1022
}
,
{
  "datetime": "2025-1206-1515",
  "pressure": 1022
}
,
{
  "datetime": "2025-1206-1528",
  "pressure": 1022
}
,
{
  "datetime": "2025-1206-1542",
  "pressure": 1022
}
,
{
  "datetime": "2025-1206-1552",
  "pressure": 1022
}
,
{
  "datetime": "2025-1206-1600",
  "pressure": 1022
}
,
{
  "datetime": "2025-1206-1614",
  "pressure": 1022
}
,
{
  "datetime": "2025-1206-1625",
  "pressure": 1022
}
,
{
  "datetime": "2025-1206-1631",
  "pressure": 1022
}
,
{
  "datetime": "2025-1206-1640",
  "pressure": 1021
}
,
{
  "datetime": "2025-1206-1650",
  "pressure": 1021
}
,
{
  "datetime": "2025-1206-1700",
  "pressure": 1021
}
,
{
  "datetime": "2025-1206-1715",
  "pressure": 1021
}
,
{
  "datetime": "2025-1206-1727",
  "pressure": 1021
}
,
{
  "datetime": "2025-1206-1738",
  "pressure": 1022
}
,
{
  "datetime": "2025-1206-1747",
  "pressure": 1022
}
,
{
  "datetime": "2025-1206-1754",
  "pressure": 1022
}
,
{
  "datetime": "2025-1206-1800",
  "pressure": 1022
}
,
{
  "datetime": "2025-1206-1814",
  "pressure": 1022
}
,
{
  "datetime": "2025-1206-1826",
  "pressure": 1022
}
,
{
  "datetime": "2025-1206-1834",
  "pressure": 1022
}
,
{
  "datetime": "2025-1206-1841",
  "pressure": 1022
}
,
{
  "datetime": "2025-1206-1850",
  "pressure": 1022
}
,
{
  "datetime": "2025-1206-1900",
  "pressure": 1022
}
,
{
  "datetime": "2025-1206-1914",
  "pressure": 1022
}
,
{
  "datetime": "2025-1206-1926",
  "pressure": 1022
}
,
{
  "datetime": "2025-1206-1936",
  "pressure": 1021
}
,
{
  "datetime": "2025-1206-1943",
  "pressure": 1021
}
,
{
  "datetime": "2025-1206-1950",
  "pressure": 1021
}
,
{
  "datetime": "2025-1206-2000",
  "pressure": 1021
}
,
{
  "datetime": "2025-1206-2013",
  "pressure": 1021
}
,
{
  "datetime": "2025-1206-2023",
  "pressure": 1021
}
,
{
  "datetime": "2025-1206-2030",
  "pressure": 1021
}
,
{
  "datetime": "2025-1206-2041",
  "pressure": 1021
}
,
{
  "datetime": "2025-1206-2050",
  "pressure": 1021
}
,
{
  "datetime": "2025-1206-2100",
  "pressure": 1021
}
,
{
  "datetime": "2025-1206-2115",
  "pressure": 1021
}
,
{
  "datetime": "2025-1206-2130",
  "pressure": 1021
}
,
{
  "datetime": "2025-1206-2154",
  "pressure": 1021
}
,
{
  "datetime": "2025-1206-2207",
  "pressure": 1021
}
,
{
  "datetime": "2025-1206-2218",
  "pressure": 1021
}
,
{
  "datetime": "2025-1206-2232",
  "pressure": 1021
}
]
