[
{
  "datetime": "2025-1216-0940",
  "pressure": 1022
}
,
{
  "datetime": "2025-1216-1014",
  "pressure": 1022
}
,
{
  "datetime": "2025-1216-1057",
  "pressure": 1021
}
,
{
  "datetime": "2025-1216-1139",
  "pressure": 1020
}
,
{
  "datetime": "2025-1216-1213",
  "pressure": 1020
}
,
{
  "datetime": "2025-1216-1244",
  "pressure": 1019
}
,
{
  "datetime": "2025-1216-1305",
  "pressure": 1019
}
,
{
  "datetime": "2025-1216-1321",
  "pressure": 1019
}
,
{
  "datetime": "2025-1216-1341",
  "pressure": 1019
}
,
{
  "datetime": "2025-1216-1356",
  "pressure": 1019
}
,
{
  "datetime": "2025-1216-1405",
  "pressure": 1019
}
,
{
  "datetime": "2025-1216-1415",
  "pressure": 1019
}
,
{
  "datetime": "2025-1216-1428",
  "pressure": 1019
}
,
{
  "datetime": "2025-1216-1439",
  "pressure": 1019
}
,
{
  "datetime": "2025-1216-1448",
  "pressure": 1019
}
,
{
  "datetime": "2025-1216-1454",
  "pressure": 1019
}
,
{
  "datetime": "2025-1216-1500",
  "pressure": 1019
}
,
{
  "datetime": "2025-1216-1515",
  "pressure": 1019
}
,
{
  "datetime": "2025-1216-1529",
  "pressure": 1019
}
,
{
  "datetime": "2025-1216-1548",
  "pressure": 1019
}
,
{
  "datetime": "2025-1216-1559",
  "pressure": 1019
}
,
{
  "datetime": "2025-1216-1611",
  "pressure": 1019
}
,
{
  "datetime": "2025-1216-1627",
  "pressure": 1019
}
,
{
  "datetime": "2025-1216-1637",
  "pressure": 1019
}
,
{
  "datetime": "2025-1216-1644",
  "pressure": 1019
}
,
{
  "datetime": "2025-1216-1651",
  "pressure": 1019
}
,
{
  "datetime": "2025-1216-1700",
  "pressure": 1019
}
,
{
  "datetime": "2025-1216-1715",
  "pressure": 1019
}
,
{
  "datetime": "2025-1216-1729",
  "pressure": 1019
}
,
{
  "datetime": "2025-1216-1745",
  "pressure": 1019
}
,
{
  "datetime": "2025-1216-1756",
  "pressure": 1019
}
,
{
  "datetime": "2025-1216-1805",
  "pressure": 1019
}
,
{
  "datetime": "2025-1216-1816",
  "pressure": 1019
}
,
{
  "datetime": "2025-1216-1829",
  "pressure": 1019
}
,
{
  "datetime": "2025-1216-1841",
  "pressure": 1019
}
,
{
  "datetime": "2025-1216-1853",
  "pressure": 1019
}
,
{
  "datetime": "2025-1216-1900",
  "pressure": 1019
}
,
{
  "datetime": "2025-1216-1915",
  "pressure": 1019
}
,
{
  "datetime": "2025-1216-1927",
  "pressure": 1019
}
,
{
  "datetime": "2025-1216-1941",
  "pressure": 1019
}
,
{
  "datetime": "2025-1216-1953",
  "pressure": 1019
}
,
{
  "datetime": "2025-1216-2000",
  "pressure": 1019
}
,
{
  "datetime": "2025-1216-2014",
  "pressure": 1019
}
,
{
  "datetime": "2025-1216-2026",
  "pressure": 1019
}
,
{
  "datetime": "2025-1216-2035",
  "pressure": 1018
}
,
{
  "datetime": "2025-1216-2042",
  "pressure": 1018
}
,
{
  "datetime": "2025-1216-2051",
  "pressure": 1018
}
,
{
  "datetime": "2025-1216-2101",
  "pressure": 1018
}
,
{
  "datetime": "2025-1216-2117",
  "pressure": 1018
}
,
{
  "datetime": "2025-1216-2132",
  "pressure": 1018
}
,
{
  "datetime": "2025-1216-2157",
  "pressure": 1018
}
,
{
  "datetime": "2025-1216-2217",
  "pressure": 1018
}
,
{
  "datetime": "2025-1216-2232",
  "pressure": 1018
}
,
{
  "datetime": "2025-1216-2250",
  "pressure": 1018
}
,
{
  "datetime": "2025-1216-2301",
  "pressure": 1018
}
,
{
  "datetime": "2025-1216-2315",
  "pressure": 1018
}
,
{
  "datetime": "2025-1216-2327",
  "pressure": 1018
}
,
{
  "datetime": "2025-1216-2341",
  "pressure": 1018
}
,
{
  "datetime": "2025-1216-2354",
  "pressure": 1018
}
,
{
  "datetime": "2025-1217-0001",
  "pressure": 1018
}
,
{
  "datetime": "2025-1217-0015",
  "pressure": 1018
}
,
{
  "datetime": "2025-1217-0028",
  "pressure": 1018
}
,
{
  "datetime": "2025-1217-0039",
  "pressure": 1018
}
,
{
  "datetime": "2025-1217-0047",
  "pressure": 1018
}
,
{
  "datetime": "2025-1217-0054",
  "pressure": 1018
}
,
{
  "datetime": "2025-1217-0100",
  "pressure": 1018
}
,
{
  "datetime": "2025-1217-0115",
  "pressure": 1018
}
,
{
  "datetime": "2025-1217-0129",
  "pressure": 1018
}
,
{
  "datetime": "2025-1217-0144",
  "pressure": 1018
}
,
{
  "datetime": "2025-1217-0156",
  "pressure": 1018
}
,
{
  "datetime": "2025-1217-0206",
  "pressure": 1018
}
,
{
  "datetime": "2025-1217-0217",
  "pressure": 1018
}
,
{
  "datetime": "2025-1217-0231",
  "pressure": 1018
}
,
{
  "datetime": "2025-1217-0245",
  "pressure": 1018
}
,
{
  "datetime": "2025-1217-0252",
  "pressure": 1018
}
,
{
  "datetime": "2025-1217-0301",
  "pressure": 1018
}
,
{
  "datetime": "2025-1217-0315",
  "pressure": 1018
}
,
{
  "datetime": "2025-1217-0329",
  "pressure": 1018
}
,
{
  "datetime": "2025-1217-0346",
  "pressure": 1018
}
,
{
  "datetime": "2025-1217-0357",
  "pressure": 1018
}
,
{
  "datetime": "2025-1217-0405",
  "pressure": 1018
}
,
{
  "datetime": "2025-1217-0415",
  "pressure": 1018
}
,
{
  "datetime": "2025-1217-0426",
  "pressure": 1018
}
,
{
  "datetime": "2025-1217-0433",
  "pressure": 1018
}
,
{
  "datetime": "2025-1217-0441",
  "pressure": 1018
}
,
{
  "datetime": "2025-1217-0450",
  "pressure": 1018
}
,
{
  "datetime": "2025-1217-0500",
  "pressure": 1018
}
,
{
  "datetime": "2025-1217-0515",
  "pressure": 1018
}
,
{
  "datetime": "2025-1217-0527",
  "pressure": 1018
}
,
{
  "datetime": "2025-1217-0538",
  "pressure": 1019
}
,
{
  "datetime": "2025-1217-0547",
  "pressure": 1019
}
,
{
  "datetime": "2025-1217-0554",
  "pressure": 1019
}
,
{
  "datetime": "2025-1217-0601",
  "pressure": 1019
}
,
{
  "datetime": "2025-1217-0614",
  "pressure": 1019
}
,
{
  "datetime": "2025-1217-0627",
  "pressure": 1019
}
,
{
  "datetime": "2025-1217-0635",
  "pressure": 1019
}
,
{
  "datetime": "2025-1217-0643",
  "pressure": 1019
}
,
{
  "datetime": "2025-1217-0650",
  "pressure": 1019
}
,
{
  "datetime": "2025-1217-0700",
  "pressure": 1019
}
,
{
  "datetime": "2025-1217-0714",
  "pressure": 1019
}
,
{
  "datetime": "2025-1217-0726",
  "pressure": 1019
}
,
{
  "datetime": "2025-1217-0736",
  "pressure": 1020
}
,
{
  "datetime": "2025-1217-0744",
  "pressure": 1020
}
,
{
  "datetime": "2025-1217-0751",
  "pressure": 1020
}
,
{
  "datetime": "2025-1217-0800",
  "pressure": 1020
}
,
{
  "datetime": "2025-1217-0814",
  "pressure": 1020
}
,
{
  "datetime": "2025-1217-0826",
  "pressure": 1020
}
,
{
  "datetime": "2025-1217-0834",
  "pressure": 1020
}
,
{
  "datetime": "2025-1217-0842",
  "pressure": 1020
}
,
{
  "datetime": "2025-1217-0850",
  "pressure": 1020
}
,
{
  "datetime": "2025-1217-0901",
  "pressure": 1020
}
,
{
  "datetime": "2025-1217-0937",
  "pressure": 1020
}
]
