{"coord":{"lon":139.638,"lat":35.4437},"weather":[{"id":701,"main":"Mist","description":"mist","icon":"50n"},{"id":500,"main":"Rain","description":"light rain","icon":"10n"}],"base":"stations","main":{"temp":4,"feels_like":-0.85,"temp_min":3.6,"temp_max":4.01,"pressure":1013,"humidity":91,"sea_level":1013,"grnd_level":1013},"visibility":4000,"wind":{"speed":7.2,"deg":350},"rain":{"1h":0.56},"clouds":{"all":75},"dt":1765648221,"sys":{"type":2,"id":20777,"country":"JP","sunrise":1765662147,"sunset":1765697378},"timezone":32400,"id":1848354,"name":"Yokohama","cod":200}