{"coord":{"lon":139.638,"lat":35.4437},"weather":[{"id":800,"main":"Clear","description":"clear sky","icon":"01n"}],"base":"stations","main":{"temp":11.72,"feels_like":10.54,"temp_min":10.9,"temp_max":12.82,"pressure":1027,"humidity":61,"sea_level":1027,"grnd_level":1026},"visibility":10000,"wind":{"speed":6.17,"deg":360},"clouds":{"all":0},"dt":1762195192,"sys":{"type":2,"id":20777,"country":"JP","sunrise":1762203936,"sunset":1762242261},"timezone":32400,"id":1848354,"name":"Yokohama","cod":200}