{"coord":{"lon":139.6368,"lat":35.4444},"weather":[{"id":501,"main":"Rain","description":"moderate rain","icon":"10n"}],"base":"stations","main":{"temp":6.34,"feels_like":3.44,"temp_min":5.32,"temp_max":7.25,"pressure":1022,"humidity":72,"sea_level":1022,"grnd_level":1022},"visibility":10000,"wind":{"speed":4.12,"deg":310},"rain":{"1h":2.37},"clouds":{"all":75},"dt":1766522709,"sys":{"type":2,"id":2033467,"country":"JP","sunrise":1766526480,"sunset":1766561617},"timezone":32400,"id":1848354,"name":"Yokohama","cod":200}