{"coord":{"lon":139.638,"lat":35.4437},"weather":[{"id":801,"main":"Clouds","description":"few clouds","icon":"02n"}],"base":"stations","main":{"temp":12.13,"feels_like":11.1,"temp_min":11.17,"temp_max":12.56,"pressure":1020,"humidity":65,"sea_level":1020,"grnd_level":1020},"visibility":10000,"wind":{"speed":1.54,"deg":150},"clouds":{"all":20},"dt":1763628150,"sys":{"type":2,"id":2033467,"country":"JP","sunrise":1763587293,"sunset":1763623966},"timezone":32400,"id":1848354,"name":"Yokohama","cod":200}