{"coord":{"lon":139.638,"lat":35.4437},"weather":[{"id":803,"main":"Clouds","description":"broken clouds","icon":"04d"}],"base":"stations","main":{"temp":9.33,"feels_like":7.38,"temp_min":8.9,"temp_max":10.12,"pressure":1027,"humidity":61,"sea_level":1027,"grnd_level":1027},"visibility":10000,"wind":{"speed":3.6,"deg":30},"clouds":{"all":75},"dt":1766473118,"sys":{"type":2,"id":2033467,"country":"JP","sunrise":1766440053,"sunset":1766475185},"timezone":32400,"id":1848354,"name":"Yokohama","cod":200}