{"coord":{"lon":139.6368,"lat":35.4444},"weather":[{"id":801,"main":"Clouds","description":"few clouds","icon":"02n"}],"base":"stations","main":{"temp":9.66,"feels_like":9.22,"temp_min":8.38,"temp_max":10.66,"pressure":1022,"humidity":60,"sea_level":1022,"grnd_level":1021},"visibility":10000,"wind":{"speed":1.54,"deg":120},"clouds":{"all":20},"dt":1765010773,"sys":{"type":2,"id":2033467,"country":"JP","sunrise":1764970584,"sunset":1765006120},"timezone":32400,"id":1848354,"name":"Yokohama","cod":200}