{"coord":{"lon":139.638,"lat":35.4437},"weather":[{"id":803,"main":"Clouds","description":"broken clouds","icon":"04n"}],"base":"stations","main":{"temp":17.01,"feels_like":17.06,"temp_min":16.17,"temp_max":17.21,"pressure":1020,"humidity":88,"sea_level":1020,"grnd_level":1020},"visibility":10000,"wind":{"speed":3.6,"deg":10},"clouds":{"all":75},"dt":1760456350,"sys":{"type":2,"id":20777,"country":"JP","sunrise":1760474833,"sunset":1760515622},"timezone":32400,"id":1848354,"name":"Yokohama","cod":200}