{"coord":{"lon":139.638,"lat":35.4437},"weather":[{"id":803,"main":"Clouds","description":"broken clouds","icon":"04d"}],"base":"stations","main":{"temp":34.45,"feels_like":41.45,"temp_min":34,"temp_max":34.78,"pressure":1011,"humidity":63,"sea_level":1011,"grnd_level":1010},"visibility":10000,"wind":{"speed":7.2,"deg":180},"clouds":{"all":75},"dt":1756871203,"sys":{"type":2,"id":20777,"country":"JP","sunrise":1756844107,"sunset":1756890429},"timezone":32400,"id":1848354,"name":"Yokohama","cod":200}